pds_image_converter/__init__.py
pds_image_converter/__main__.py
pds_image_converter/cli.py
pds_image_converter/config.py
pds_image_converter/converter.py
pds_image_converter/decorators.py
pds_image_converter/filters.py
pds_image_converter/fpn.py
pds_image_converter/image.py
pds_image_converter/methods.py
pds_image_converter/output_locator.py
pds_image_converter/py.typed
pds_image_converter/quick.py
pds_image_converter/readers.py
pds_image_converter/registers.py
pds_image_converter/serializer.py
pds_image_converter/utils.py
pds_image_converter/writers.py
pds_image_converter/configs/__init__.py
pds_image_converter/configs/janus2quicklook.toml
pds_image_converter/configs/janus2thumbnail.toml
pds_image_converter/configs/janus_raw2quicklook.toml
pds_image_converter/data/__init__.py
pds_image_converter/data/fpn_calibration_pipeline.npz
pds_image_converter-0.1.8.dist-info/METADATA
pds_image_converter-0.1.8.dist-info/WHEEL
pds_image_converter-0.1.8.dist-info/entry_points.txt
pds_image_converter-0.1.8.dist-info/licenses/LICENSE
pds_image_converter-0.1.8.dist-info/RECORD
