Metadata-Version: 2.4
Name: pds-image-converter
Version: 0.1.8
Project-URL: Homepage, https://JANUS-JUICE.github.io/pds-image-converter
Project-URL: Repository, https://github.com/JANUS-JUICE/pds-image-converter
Project-URL: Documentation, https://JANUS-JUICE.github.io/pds-image-converter
Author-email: Luca Penasa <luca.penasa@inaf.it>
License-Expression: MIT
License-File: LICENSE
Classifier: Development Status :: 4 - Beta
Classifier: Intended Audience :: Developers
Classifier: Operating System :: OS Independent
Classifier: Programming Language :: Python
Classifier: Programming Language :: Python :: 3
Classifier: Programming Language :: Python :: 3.10
Classifier: Programming Language :: Python :: 3.11
Classifier: Programming Language :: Python :: 3.12
Classifier: Topic :: Software Development :: Libraries :: Python Modules
Classifier: Typing :: Typed
Requires-Python: <4.0,>=3.10
Requires-Dist: astropy>=5.0.0
Requires-Dist: attrs>=21.0.0
Requires-Dist: cattrs>=23
Requires-Dist: click<9,>=8.1.7
Requires-Dist: janusreader>=0.10.0
Requires-Dist: loguru>=0.7.0
Requires-Dist: numpy>=2.2.6
Requires-Dist: pdr<2,>=1.2.3
Requires-Dist: pillow<11,>=10.3.0
